{
  "users": [
    {
      "id": 1,
      "email": "alex@alex.com",
      "password": "$argon2id$v=19$m=65536,t=3,p=4$KaiN84ePxNJsewC1yEH9zQ$dSBMx/nGeTmbX5ZzhdLDgYLRyPcdg0v8SIz9tHJSZE8",
      "name": "Alexandre",
      "createdAt": "2025-06-05T15:17:28.403Z"
    },
    {
      "id": 2,
      "email": "toto@toto.com",
      "password": "$argon2id$v=19$m=65536,t=3,p=4$irPwhR5Zlp88vHHAMCrxBw$SZ9BG6QVwCFkDIJd/iIWDA/oWgK2TnF0TTJyr+2x4C4",
      "name": "toto",
      "createdAt": "2025-06-05T15:17:28.404Z"
    },
    {
      "id": 3,
      "email": "tata@tata.com",
      "password": "$argon2id$v=19$m=65536,t=3,p=4$WdhvdPhhoSGyYck916oZeg$Wkpb/KsjZIiTkQuFyA9N7lpOHqIJzVqG9ejG27waH+c",
      "name": "tata",
      "createdAt": "2025-06-05T15:17:28.408Z"
    },
    {
      "id": 4,
      "email": "tutu@tutu.com",
      "password": "$argon2id$v=19$m=65536,t=3,p=4$twEPNp3t2OZ4jqSTBXX40Q$D0H1SkAPGnJLZBX52PBn2P+Al1yFCNazDNMihkilRJo",
      "name": "tutu",
      "createdAt": "2025-06-05T15:17:28.409Z"
    },
    {
      "id": 5,
      "email": "titi@titi.com",
      "password": "$argon2id$v=19$m=65536,t=3,p=4$SswB60tVLqmiwBjRYpPLgw$PDoLa2MrirbT1eS8ulJ6yPZaEqLLuX6sbl60QinDwE8",
      "name": "titi",
      "createdAt": "2025-06-05T15:17:28.442Z"
    },
    {
      "id": 6,
      "email": "admin@admin.com",
      "password": "$argon2id$v=19$m=65536,t=3,p=4$SaE5Bdp/TTQRVrUchAgFKw$g6PlV2EoIhgSsqvIibvyTsr3ggh6qEi3CITiyAyt2S0",
      "name": "admin",
      "createdAt": "2025-06-05T15:17:28.441Z"
    }
  ],
  "entries": [
    {
      "id": 101,
      "userId": 1,
      "date": "2025-05-12",
      "title": "Une journée productive",
      "content": "Aujourd’hui j’ai bien avancé sur mon projet Angular. J’ai terminé l’ajout d’une entrée avec humeur.",
      "mood": "happy",
      "createdAt": "2025-06-05T15:17:28.442Z"
    },
    {
      "id": 102,
      "userId": 1,
      "date": "2025-05-12",
      "title": "Fatigue et réflexion",
      "content": "J’ai eu un coup de mou...",
      "mood": "sad",
      "createdAt": "2025-06-05T15:17:28.442Z"
    },
    {
      "id": 103,
      "userId": 2,
      "date": "2025-05-12",
      "title": "Fatigue et réflexion1",
      "content": "J’ai eu un coup de mou...",
      "mood": "sad",
      "createdAt": "2025-06-05T15:17:28.442Z"
    },
    {
      "id": 104,
      "userId": 2,
      "date": "2025-05-12",
      "title": "Fatigue et réflexion2",
      "content": "J’ai eu un coup de mou...",
      "mood": "happy",
      "createdAt": "2025-06-05T15:17:28.442Z"
    },
    {
      "id": 105,
      "userId": 2,
      "date": "2025-05-12",
      "title": "Fatigue et réflexio3",
      "content": "J’ai eu un coup de mou...",
      "mood": "sad",
      "createdAt": "2025-06-05T15:17:28.442Z"
    },
    {
      "id": 106,
      "userId": 2,
      "date": "2025-05-30",
      "title": "Fatigue et réflexion4",
      "content": "J’ai eu un coup de mou...",
      "mood": "sad",
      "createdAt": "2025-06-05T15:17:28.442Z"
    },
    {
      "id": 107,
      "userId": 2,
      "date": "2025-05-29",
      "title": "Fatigue et réflexion5",
      "content": "J’ai eu un coup de mou...",
      "mood": "happy",
      "createdAt": "2025-06-05T15:17:28.442Z"
    },
    {
      "id": 108,
      "userId": 2,
      "date": "2025-05-27",
      "title": "Fatigue et réflexion6",
      "content": "J’ai eu un coup de mou...",
      "mood": "happy",
      "createdAt": "2025-06-05T15:17:28.442Z"
    },
    {
      "id": 109,
      "userId": 2,
      "date": "2025-05-25",
      "title": "Fatigue et réflexion7",
      "content": "J’ai eu un coup de mou...",
      "mood": "sad",
      "createdAt": "2025-06-05T15:17:28.442Z"
    },
    {
      "id": 110,
      "userId": 2,
      "date": "2025-05-18",
      "title": "Fatigue et réflexion8",
      "content": "J’ai eu un coup de mou...",
      "mood": "happy",
      "createdAt": "2025-06-05T15:17:28.442Z"
    },
    {
      "id": 111,
      "userId": 2,
      "date": "2025-05-15",
      "title": "Fatigue et réflexion9",
      "content": "J’ai eu un coup de mou...",
      "mood": "sad",
      "createdAt": "2025-06-05T15:17:28.442Z"
    },
    {
      "id": 112,
      "userId": 2,
      "date": "2025-05-12",
      "title": "Fatigue et réflexion10",
      "content": "J’ai eu un coup de mou...",
      "mood": "sad",
      "createdAt": "2025-06-05T15:17:28.442Z"
    },
    {
      "id": 113,
      "userId": 2,
      "date": "2025-05-09",
      "title": "Fatigue et réflexion11",
      "content": "J’ai eu un coup de mou...",
      "mood": "sad",
      "createdAt": "2025-06-05T15:17:28.442Z"
    },
    {
      "id": 114,
      "userId": 2,
      "date": "2025-05-10",
      "title": "Fatigue et réflexion12",
      "content": "J’ai eu un coup de mou...",
      "mood": "sad",
      "createdAt": "2025-06-05T15:17:28.442Z"
    },
    {
      "id": 115,
      "userId": 2,
      "date": "2025-05-11",
      "title": "Fatigue et réflexion15",
      "content": "J’ai eu un coup de mou...",
      "mood": "neutral",
      "createdAt": "2025-06-05T15:17:28.442Z"
    },
    {
      "id": 116,
      "userId": 2,
      "date": "2025-05-12",
      "title": "Fatigue et réflexion16",
      "content": "J’ai eu un coup de mou...",
      "mood": "neutral",
      "createdAt": "2025-06-05T15:17:28.442Z"
    },
    {
      "id": 117,
      "userId": 2,
      "date": "2025-06-04",
      "title": "Fatigue et réflexion17",
      "content": "J’ai eu un coup de mou...",
      "mood": "neutral",
      "createdAt": "2025-06-05T15:17:28.442Z"
    },
    {
      "id": 118,
      "userId": 2,
      "date": "2025-06-01",
      "title": "Fatigue et réflexion18",
      "content": "J’ai eu un coup de mou...",
      "mood": "sad",
      "createdAt": "2025-06-05T15:17:28.442Z"
    },
    {
      "id": 119,
      "userId": 2,
      "date": "2025-06-02",
      "title": "Fatigue et réflexion19",
      "content": "J’ai eu un coup de mou...",
      "mood": "happy",
      "createdAt": "2025-06-05T15:17:28.442Z"
    },
    {
      "id": 120,
      "userId": 2,
      "date": "2025-06-06",
      "title": "Fatigue et réflexion20",
      "content": "J’ai eu un coup de mou...",
      "mood": "happy",
      "createdAt": "2025-06-05T15:17:28.442Z"
    }
  ]
}